mpint/__init__.py
mpint/integrate.py
mpint/pio.py
mpint/pvars.py
mpint/lib/__init__.py
mpint/lib/pe.py
mpint/lib/pe_ve.py
mpint-1.1.1.dist-info/LICENCE
mpint-1.1.1.dist-info/METADATA
mpint-1.1.1.dist-info/WHEEL
mpint-1.1.1.dist-info/top_level.txt
mpint-1.1.1.dist-info/RECORD
