Metadata-Version: 2.1
Name: mpint
Version: 1.1.1
Summary: Automatic peak integration in XY-data.
Home-page: https://github.com/mirekslouf/mpint/
Author: Mirek Slouf
Author-email: mirek.slouf@gmail.com
License: MIT
Project-URL: Documentation, https://mirekslouf.github.io/mpint/
Classifier: Programming Language :: Python :: 3
Classifier: License :: OSI Approved :: MIT License
Classifier: Operating System :: OS Independent
Requires-Python: >=3.6
License-File: LICENCE
